{"status": "success", "error": "", "algorithm": "binseg", "dataset": "mean", "data_name": "mean0", "param": {"max_cp": "max", "method": "var", "penalty": "Asymptotic", "test_stat": "CSS"}, "cp": [[0, 66.0], [67.0, 142.0], [143.0, 170.0], [171.0, 244.0], [245.0, 308.0], [309.0, 381.0], [382.0, 409.0], [410.0, 524.0], [525.0, 551.0], [552.0, 625.0], [626.0, 933.0], [934.0, 1007.0], [1008.0, 3015.0], [3016.0, 3953.0], [3954.0, 4999]], "score": {"metric": "compute_f1_score", "value": 0.19047619047619044}}