{"status": "success", "error": "", "algorithm": "hybrid_cusum_moving_window", "dataset": "energy", "data_name": "energy9", "param": {"distance_threshold": 5, "overlap_ratio": 0.9, "rank": null, "rows": 5, "singular_threshold": 5, "skip": false, "training_ratio": 0.6, "window_size": 50}, "cp": [[0, 71], [72, 179], [180, 285], [286, 401], [402, 510], [511, 620], [621, 736], [737, 839], [840, 973], [974, 1073], [1074, 1182], [1183, 1293], [1294, 1398], [1399, 1508], [1509, 1622], [1623, 1736], [1737, 1846], [1847, 1960], [1961, 2037], [2038, 2097], [2098, 2167], [2168, 3000], [3001, 3060], [3061, 3196], [3197, 3295], [3296, 3415], [3416, 3505], [3506, 3584], [3585, 3680], [3681, 3755], [3756, 3838], [3839, 3927], [3928, 3995], [3996, 4999]], "score": {"metric": "compute_f1_score", "value": 0.15}}