{"status": "success", "error": "", "algorithm": "hybrid_cusum_moving_window", "dataset": "energy", "data_name": "energy19", "param": {"distance_threshold": 5, "overlap_ratio": 0.0, "rank": null, "rows": 5, "singular_threshold": 5, "skip": false, "training_ratio": 0.6, "window_size": 50}, "cp": [[0, 223], [224, 366], [367, 536], [537, 637], [638, 815], [816, 1000], [1001, 1227], [1228, 1356], [1357, 1499], [1500, 1646], [1647, 1761], [1762, 1954], [1955, 2055], [2056, 2293], [2294, 2400], [2401, 2502], [2503, 2700], [2701, 2765], [2766, 2867], [2868, 3026], [3027, 3133], [3134, 3381], [3382, 3532], [3533, 3788], [3789, 3906], [3907, 4044], [4045, 4151], [4152, 4254], [4255, 4359], [4360, 4462], [4463, 4662], [4663, 4730], [4731, 4999]], "score": {"metric": "compute_f1_score", "value": 0.10256410256410256}}