{"status": "success", "error": "", "algorithm": "hybrid_cusum_moving_window", "dataset": "energy", "data_name": "energy19", "param": {"distance_threshold": 5, "overlap_ratio": 0.0, "rank": null, "rows": 5, "singular_threshold": 5, "skip": false, "training_ratio": 0.5, "window_size": 50}, "cp": [[0, 574], [575, 679], [680, 889], [890, 1018], [1019, 1122], [1123, 1224], [1225, 1355], [1356, 1458], [1459, 1562], [1563, 1672], [1673, 1780], [1781, 1971], [1972, 2090], [2091, 2407], [2408, 2515], [2516, 2706], [2707, 2829], [2830, 3001], [3002, 3173], [3174, 3471], [3472, 3596], [3597, 3786], [3787, 3909], [3910, 4002], [4003, 4113], [4114, 4218], [4219, 4469], [4470, 4615], [4616, 4870], [4871, 4990], [4991, 4999]], "score": {"metric": "compute_f1_score", "value": 0.2162162162162162}}