{"status": "success", "error": "", "algorithm": "hybrid_cusum_moving_window", "dataset": "energy", "data_name": "energy15", "param": {"distance_threshold": 10, "overlap_ratio": 0.0, "rank": null, "rows": 5, "singular_threshold": 5, "skip": true, "training_ratio": 0.6, "window_size": 50}, "cp": [[0, 54], [55, 279], [280, 554], [555, 674], [675, 884], [885, 994], [995, 2024], [2025, 2079], [2080, 4009], [4010, 4149], [4150, 4999]], "score": {"metric": "compute_f1_score", "value": 0.3529411764705882}}