{"status": "success", "error": "", "algorithm": "hybrid_cusum_moving_window", "dataset": "energy", "data_name": "energy16", "param": {"distance_threshold": 10, "overlap_ratio": 0.5, "rank": null, "rows": 5, "singular_threshold": 5, "skip": false, "training_ratio": 0.6, "window_size": 50}, "cp": [[0, 76], [77, 181], [182, 257], [258, 1006], [1007, 1097], [1098, 1172], [1173, 1303], [1304, 1409], [1410, 2078], [2079, 2155], [2156, 2213], [2214, 2298], [2299, 2373], [2374, 2455], [2456, 2549], [2550, 2627], [2628, 2737], [2738, 2847], [2848, 2929], [2930, 3004], [3005, 3131], [3132, 3189], [3190, 3315], [3316, 3394], [3395, 3476], [3477, 4089], [4090, 4178], [4179, 4261], [4262, 4337], [4338, 4999]], "score": {"metric": "compute_f1_score", "value": 0.16666666666666669}}