{"status": "success", "error": "", "algorithm": "microsoft_ssa", "dataset": "energy", "data_name": "energy6", "param": {"change_history_length": 10, "confidence": 95.0, "error_function": "AbsoluteProportion", "martingale": "Mixture", "power_martingale_epsilon": 0.1, "seasonal_window_size": 5, "training_window_size": 50}, "cp": [[0, 11], [12, 51], [52, 61], [62, 77], [78, 87], [88, 97], [98, 114], [115, 124], [125, 134], [135, 147], [148, 193], [194, 203], [204, 213], [214, 260], [261, 273], [274, 288], [289, 326], [327, 338], [339, 348], [349, 368], [369, 401], [402, 411], [412, 429], [430, 439], [440, 449], [450, 459], [460, 479], [480, 494], [495, 522], [523, 546], [547, 556], [557, 566], [567, 576], [577, 586], [587, 596], [597, 607], [608, 617], [618, 639], [640, 654], [655, 674], [675, 684], [685, 694], [695, 704], [705, 721], [722, 765], [766, 787], [788, 834], [835, 844], [845, 860], [861, 873], [874, 892], [893, 902], [903, 912], [913, 938], [939, 4999]], "score": {"metric": "compute_f1_score", "value": 0.032786885245901634}}