{"status": "success", "error": "", "algorithm": "microsoft_ssa", "dataset": "energy", "data_name": "energy9", "param": {"change_history_length": 10, "confidence": 95.0, "error_function": "SignedProportion", "martingale": "Power", "power_martingale_epsilon": 0.5, "seasonal_window_size": 5, "training_window_size": 400}, "cp": [[0, 8], [9, 28], [29, 67], [68, 77], [78, 89], [90, 125], [126, 139], [140, 174], [175, 184], [185, 200], [201, 222], [223, 283], [284, 293], [294, 310], [311, 332], [333, 347], [348, 394], [395, 418], [419, 456], [457, 477], [478, 502], [503, 512], [513, 532], [533, 587], [588, 611], [612, 643], [644, 663], [664, 697], [698, 716], [717, 748], [749, 760], [761, 807], [808, 821], [822, 858], [859, 884], [885, 905], [906, 918], [919, 959], [960, 969], [970, 1015], [1016, 1047], [1048, 1068], [1069, 1078], [1079, 1090], [1091, 1105], [1106, 1139], [1140, 4999]], "score": {"metric": "compute_f1_score", "value": 0.03773584905660377}}