{"status": "success", "error": "", "algorithm": "microsoft_ssa", "dataset": "energy", "data_name": "energy18", "param": {"change_history_length": 10, "confidence": 95.0, "error_function": "SignedDifference", "martingale": "Mixture", "power_martingale_epsilon": 0.5, "seasonal_window_size": 5, "training_window_size": 700}, "cp": [[0, 8], [9, 46], [47, 109], [110, 308], [309, 632], [633, 959], [960, 1121], [1122, 1188], [1189, 1316], [1317, 1537], [1538, 1578], [1579, 1800], [1801, 1934], [1935, 1999], [2000, 2162], [2163, 2228], [2229, 2584], [2585, 2780], [2781, 2846], [2847, 2880], [2881, 3000], [3001, 3999], [4000, 4116], [4117, 4149], [4150, 4342], [4343, 4505], [4506, 4537], [4538, 4928], [4929, 4994], [4995, 4999]], "score": {"metric": "compute_f1_score", "value": 0.2777777777777778}}