{"status": "success", "error": "", "algorithm": "microsoft_ssa", "dataset": "energy", "data_name": "energy18", "param": {"change_history_length": 10, "confidence": 95.0, "error_function": "AbsoluteDifference", "martingale": "Power", "power_martingale_epsilon": 0.1, "seasonal_window_size": 5, "training_window_size": 700}, "cp": [[0, 8], [9, 48], [49, 402], [403, 1308], [1309, 1544], [1545, 1772], [1773, 1933], [1934, 1967], [1968, 2577], [2578, 2780], [2781, 2813], [2814, 2840], [2841, 3000], [3001, 3999], [4000, 4081], [4082, 4115], [4116, 4309], [4310, 4498], [4499, 4537], [4538, 4733], [4734, 4920], [4921, 4999]], "score": {"metric": "compute_f1_score", "value": 0.21428571428571427}}