{"status": "success", "error": "", "algorithm": "hybrid_cusum_moving_window", "dataset": "struct", "data_name": "struct17", "param": {"distance_threshold": 10, "overlap_ratio": 0.0, "rank": null, "rows": 5, "singular_threshold": 5, "skip": true, "training_ratio": 0.6, "window_size": 50}, "cp": [[0, 54], [55, 134], [135, 289], [290, 354], [355, 434], [435, 484], [485, 534], [535, 694], [695, 754], [755, 814], [815, 899], [900, 949], [950, 999], [1000, 2109], [2110, 2999], [3000, 4069], [4070, 4124], [4125, 4219], [4220, 4274], [4275, 4379], [4380, 4434], [4435, 4539], [4540, 4594], [4595, 4699], [4700, 4754], [4755, 4864], [4865, 4924], [4925, 4999]], "score": {"metric": "compute_f1_score", "value": 0.17647058823529413}}