{"status": "success", "error": "", "algorithm": "hybrid_cusum_moving_window", "dataset": "struct", "data_name": "struct2", "param": {"distance_threshold": 10, "overlap_ratio": 0.9, "rank": null, "rows": 5, "singular_threshold": 5, "skip": false, "training_ratio": 0.6, "window_size": 50}, "cp": [[0, 77], [78, 150], [151, 215], [216, 284], [285, 355], [356, 412], [413, 476], [477, 549], [550, 607], [608, 688], [689, 753], [754, 851], [852, 914], [915, 989], [990, 2000], [2001, 2126], [2127, 2195], [2196, 2285], [2286, 2350], [2351, 2421], [2422, 2492], [2493, 2559], [2560, 2629], [2630, 2731], [2732, 2821], [2822, 2900], [2901, 3000], [3001, 4000], [4001, 4079], [4080, 4137], [4138, 4283], [4284, 4356], [4357, 4490], [4491, 4593], [4594, 4708], [4709, 4836], [4837, 4956], [4957, 4999]], "score": {"metric": "compute_f1_score", "value": 0.22727272727272727}}