{"status": "success", "error": "", "algorithm": "hybrid_cusum_moving_window", "dataset": "struct", "data_name": "struct0", "param": {"distance_threshold": 10, "overlap_ratio": 0.5, "rank": null, "rows": 15, "singular_threshold": 5, "skip": false, "training_ratio": 0.6, "window_size": 200}, "cp": [[0, 231], [232, 468], [469, 802], [803, 1012], [1013, 2000], [2001, 2330], [2331, 2689], [2690, 3028], [3029, 3327], [3328, 3753], [3754, 4000], [4001, 4443], [4444, 4999]], "score": {"metric": "compute_f1_score", "value": 0.3157894736842105}}