{"status": "success", "error": "", "algorithm": "mSSA", "dataset": "hasc", "data_name": "HASC1004", "param": {"distance_threshold": 5, "normalize": true, "rank": null, "rows": 30, "singular_threshold": 5, "skip": false, "training_ratio": 0.5, "window_size": 700}, "cp": [[0, 734], [735, 1461], [1462, 2333], [2334, 3096], [3097, 3944], [3945, 4886], [4887, 6020], [6021, 7159], [7160, 7948], [7949, 8849], [8850, 9651], [9652, 10880], [10881, 11760], [11761, 11842]], "score": {"metric": "compute_f1_score", "value": 0.16}}