{"status": "success", "error": "", "algorithm": "mSSA", "dataset": "hasc", "data_name": "HASC1002", "param": {"distance_threshold": 5, "normalize": false, "rank": null, "rows": 15, "singular_threshold": 5, "skip": true, "training_ratio": 0.5, "window_size": 200}, "cp": [[0, 1094], [1095, 1814], [1815, 2189], [2190, 2864], [2865, 4139], [4140, 4844], [4845, 6314], [6315, 7169], [7170, 9014], [9015, 10034], [10035, 10694], [10695, 10964], [10965, 11767]], "score": {"metric": "compute_f1_score", "value": 0.32}}