{"status": "success", "error": "", "algorithm": "mssa_mw", "dataset": "struct", "data_name": "struct5", "param": {"distance_threshold": 10, "normalize": true, "overlap_ratio": 0.5, "rank": null, "rows": 15, "singular_threshold": 2, "skip": false, "training_ratio": 0.5, "window_size": 200}, "cp": [[0, 311], [312, 615], [616, 918], [919, 1143], [1144, 1361], [1362, 1592], [1593, 1899], [1900, 2259], [2260, 2561], [2562, 2781], [2782, 3083], [3084, 3361], [3362, 3664], [3665, 3990], [3991, 4436], [4437, 4659], [4660, 4999]], "score": {"metric": "compute_f1_score", "value": 0.1739130434782609}}