{"status": "success", "error": "", "algorithm": "hybrid_cusum_moving_window", "dataset": "mean", "data_name": "mean12", "param": {"distance_threshold": 5, "overlap_ratio": 0.0, "rank": null, "rows": 5, "singular_threshold": 2, "skip": false, "training_ratio": 0.5, "window_size": 50}, "cp": [[0, 102], [103, 1001], [1002, 1103], [1104, 1278], [1279, 1427], [1428, 1529], [1530, 1691], [1692, 2000], [2001, 2162], [2163, 2310], [2311, 2468], [2469, 2568], [2569, 2705], [2706, 2806], [2807, 3359], [3360, 3512], [3513, 3613], [3614, 3770], [3771, 4017], [4018, 4999]], "score": {"metric": "compute_f1_score", "value": 0.23076923076923075}}