{"status": "success", "error": "", "algorithm": "hybrid_cusum_moving_window", "dataset": "mean", "data_name": "mean12", "param": {"distance_threshold": 5, "overlap_ratio": 0.9, "rank": null, "rows": 15, "singular_threshold": 2, "skip": false, "training_ratio": 0.5, "window_size": 400}, "cp": [[0, 550], [551, 1001], [1002, 1530], [1531, 2002], [2003, 2532], [2533, 3131], [3132, 3728], [3729, 4443], [4444, 4969], [4970, 4999]], "score": {"metric": "compute_f1_score", "value": 0.37499999999999994}}