{"status": "success", "error": "", "algorithm": "hybrid_cusum_moving_window", "dataset": "mean", "data_name": "mean12", "param": {"distance_threshold": 10, "overlap_ratio": 0.5, "rank": null, "rows": 15, "singular_threshold": 5, "skip": false, "training_ratio": 0.5, "window_size": 200}, "cp": [[0, 308], [309, 792], [793, 1088], [1089, 1490], [1491, 1807], [1808, 2113], [2114, 2499], [2500, 2798], [2799, 3193], [3194, 3496], [3497, 3802], [3803, 4012], [4013, 4407], [4408, 4834], [4835, 4999]], "score": {"metric": "compute_f1_score", "value": 0.09523809523809522}}