{"status": "success", "error": "", "algorithm": "hybrid_cusum_moving_window", "dataset": "mean", "data_name": "mean14", "param": {"distance_threshold": 5, "overlap_ratio": 0.9, "rank": null, "rows": 15, "singular_threshold": 2, "skip": false, "training_ratio": 0.5, "window_size": 200}, "cp": [[0, 214], [215, 432], [433, 643], [644, 871], [872, 1131], [1132, 1344], [1345, 1565], [1566, 1784], [1785, 1994], [1995, 2206], [2207, 2422], [2423, 2632], [2633, 2848], [2849, 3076], [3077, 3295], [3296, 3510], [3511, 3725], [3726, 3936], [3937, 4999]], "score": {"metric": "compute_f1_score", "value": 0.16}}