{"status": "success", "error": "", "algorithm": "mssa_mw", "dataset": "hasc", "data_name": "HASC1009", "param": {"distance_threshold": 10, "normalize": true, "overlap_ratio": 0.0, "rank": null, "rows": 5, "singular_threshold": 5, "skip": false, "training_ratio": 0.6, "window_size": 200}, "cp": [[0, 403], [404, 812], [813, 1052], [1053, 1467], [1468, 1919], [1920, 2424], [2425, 2844], [2845, 3247], [3248, 3688], [3689, 4093], [4094, 4587], [4588, 4987], [4988, 5414], [5415, 5832], [5833, 6278], [6279, 6841], [6842, 7189], [7190, 7617], [7618, 8022], [8023, 8427], [8428, 8840], [8841, 9249], [9250, 9662], [9663, 10065], [10066, 10552], [10553, 10952], [10953, 11164], [11165, 11585], [11586, 11772]], "score": {"metric": "compute_f1_score", "value": 0.1951219512195122}}