{"status": "success", "error": "", "algorithm": "mssa_mw", "dataset": "hasc", "data_name": "HASC1003", "param": {"distance_threshold": 10, "normalize": true, "overlap_ratio": 0.9, "rank": null, "rows": 30, "singular_threshold": 2, "skip": false, "training_ratio": 0.6, "window_size": 700}, "cp": [[0, 1209], [1210, 2809], [2810, 3610], [3611, 4662], [4663, 5561], [5562, 6832], [6833, 7647], [7648, 8622], [8623, 9491], [9492, 10629], [10630, 11999]], "score": {"metric": "compute_f1_score", "value": 0.18181818181818182}}