{"status": "success", "error": "", "algorithm": "mssa_mw", "dataset": "hasc", "data_name": "HASC1017", "param": {"distance_threshold": 10, "normalize": true, "overlap_ratio": 0.0, "rank": null, "rows": 30, "singular_threshold": 5, "skip": false, "training_ratio": 0.6, "window_size": 400}, "cp": [[0, 666], [667, 1447], [1448, 2228], [2229, 3008], [3009, 3797], [3798, 4598], [4599, 5389], [5390, 6175], [6176, 6976], [6977, 7777], [7778, 8850], [8851, 9322], [9323, 10102], [10103, 11027], [11028, 11452], [11453, 11853]], "score": {"metric": "compute_f1_score", "value": 0.07142857142857144}}