{"status": "success", "error": "", "algorithm": "mssa_mw", "dataset": "hasc", "data_name": "HASC1015", "param": {"distance_threshold": 10, "normalize": true, "overlap_ratio": 0.0, "rank": null, "rows": 5, "singular_threshold": 5, "skip": false, "training_ratio": 0.6, "window_size": 400}, "cp": [[0, 813], [814, 1618], [1619, 2419], [2420, 3219], [3220, 4029], [4030, 4840], [4841, 5644], [5645, 6447], [6448, 7247], [7248, 8048], [8049, 8908], [8909, 9740], [9741, 10715], [10716, 11557], [11558, 11737]], "score": {"metric": "compute_f1_score", "value": 0.07407407407407407}}