{"status": "success", "error": "", "algorithm": "mssa_mw", "dataset": "hasc", "data_name": "HASC1003", "param": {"distance_threshold": 10, "normalize": true, "overlap_ratio": 0.0, "rank": null, "rows": 15, "singular_threshold": 2, "skip": false, "training_ratio": 0.5, "window_size": 400}, "cp": [[0, 702], [703, 1493], [1494, 2411], [2412, 2909], [2910, 3362], [3363, 4142], [4143, 4944], [4945, 5811], [5812, 6601], [6602, 7406], [7407, 8305], [8306, 9092], [9093, 9879], [9880, 10850], [10851, 11632], [11633, 11999]], "score": {"metric": "compute_f1_score", "value": 0.07407407407407407}}