{"status": "success", "error": "", "algorithm": "mssa_mw", "dataset": "hasc", "data_name": "HASC1016", "param": {"distance_threshold": 10, "normalize": true, "overlap_ratio": 0.0, "rank": null, "rows": 30, "singular_threshold": 5, "skip": false, "training_ratio": 0.5, "window_size": 400}, "cp": [[0, 480], [481, 1260], [1261, 1682], [1683, 2463], [2464, 2966], [2967, 3420], [3421, 3840], [3841, 4264], [4265, 4701], [4702, 5497], [5498, 6288], [6289, 7142], [7143, 8111], [8112, 8560], [8561, 9343], [9344, 10123], [10124, 10573], [10574, 10993], [10994, 11413], [11414, 11833], [11834, 11999]], "score": {"metric": "compute_f1_score", "value": 0.18181818181818182}}