{"status": "success", "error": "", "algorithm": "mssa_mw", "dataset": "hasc", "data_name": "HASC1005", "param": {"distance_threshold": 5, "normalize": true, "overlap_ratio": 0.5, "rank": null, "rows": 15, "singular_threshold": 5, "skip": false, "training_ratio": 0.6, "window_size": 400}, "cp": [[0, 602], [603, 1171], [1172, 1762], [1763, 2710], [2711, 3317], [3318, 3781], [3782, 4384], [4385, 4990], [4991, 5575], [5576, 6230], [6231, 6710], [6711, 7336], [7337, 8027], [8028, 8616], [8617, 9249], [9250, 9860], [9861, 10538], [10539, 11133], [11134, 11764], [11765, 11815]], "score": {"metric": "compute_f1_score", "value": 0.12903225806451613}}