{"status": "success", "error": "", "algorithm": "mssa_mw", "dataset": "hasc", "data_name": "HASC1012", "param": {"distance_threshold": 5, "normalize": true, "overlap_ratio": 0.9, "rank": null, "rows": 5, "singular_threshold": 2, "skip": false, "training_ratio": 0.6, "window_size": 400}, "cp": [[0, 970], [971, 1434], [1435, 2825], [2826, 3232], [3233, 3646], [3647, 4060], [4061, 4516], [4517, 4984], [4985, 5438], [5439, 6837], [6838, 7509], [7510, 8094], [8095, 8565], [8566, 9702], [9703, 10162], [10163, 10570], [10571, 10977], [10978, 11382], [11383, 11742]], "score": {"metric": "compute_f1_score", "value": 0.1935483870967742}}