{"status": "success", "error": "", "algorithm": "mssa_mw", "dataset": "hasc", "data_name": "HASC1016", "param": {"distance_threshold": 10, "normalize": true, "overlap_ratio": 0.5, "rank": null, "rows": 5, "singular_threshold": 2, "skip": false, "training_ratio": 0.6, "window_size": 400}, "cp": [[0, 1095], [1096, 2135], [2136, 2985], [2986, 4009], [4010, 4692], [4693, 5439], [5440, 6121], [6122, 6988], [6989, 7442], [7443, 8103], [8104, 9140], [9141, 9968], [9969, 11151], [11152, 11820], [11821, 11999]], "score": {"metric": "compute_f1_score", "value": 0.3703703703703704}}