{"status": "success", "error": "", "algorithm": "mssa_mw", "dataset": "hasc", "data_name": "HASC1013", "param": {"distance_threshold": 10, "normalize": true, "overlap_ratio": 0.5, "rank": null, "rows": 5, "singular_threshold": 2, "skip": false, "training_ratio": 0.6, "window_size": 400}, "cp": [[0, 842], [843, 1488], [1489, 1893], [1894, 2628], [2629, 3228], [3229, 3633], [3634, 4038], [4039, 4746], [4747, 5157], [5158, 5804], [5805, 6410], [6411, 7019], [7020, 7743], [7744, 8393], [8394, 9112], [9113, 9951], [9952, 10586], [10587, 11186], [11187, 11591], [11592, 11996], [11997, 11999]], "score": {"metric": "compute_f1_score", "value": 0.060606060606060615}}