{"status": "success", "error": "", "algorithm": "mssa_mw", "dataset": "hasc", "data_name": "HASC1018", "param": {"distance_threshold": 10, "normalize": true, "overlap_ratio": 0.9, "rank": null, "rows": 30, "singular_threshold": 2, "skip": false, "training_ratio": 0.6, "window_size": 400}, "cp": [[0, 744], [745, 1201], [1202, 1657], [1658, 2497], [2498, 2953], [2954, 3399], [3400, 3909], [3910, 4569], [4570, 5065], [5066, 5557], [5558, 6318], [6319, 6812], [6813, 7452], [7453, 8007], [8008, 9593], [9594, 10035], [10036, 10611], [10612, 11056], [11057, 11564], [11565, 11768]], "score": {"metric": "compute_f1_score", "value": 0.18749999999999997}}