{"status": "success", "error": "", "algorithm": "mssa_mw", "dataset": "hasc", "data_name": "HASC1018", "param": {"distance_threshold": 10, "normalize": true, "overlap_ratio": 0.5, "rank": null, "rows": 5, "singular_threshold": 5, "skip": false, "training_ratio": 0.5, "window_size": 400}, "cp": [[0, 1087], [1088, 1677], [1678, 2753], [2754, 3385], [3386, 3835], [3836, 5054], [5055, 5677], [5678, 6315], [6316, 6917], [6918, 7373], [7374, 8102], [8103, 8973], [8974, 9786], [9787, 11046], [11047, 11768]], "score": {"metric": "compute_f1_score", "value": 0.07407407407407407}}