{"status": "success", "error": "", "algorithm": "mssa_mw", "dataset": "hasc", "data_name": "HASC1011", "param": {"distance_threshold": 10, "normalize": true, "overlap_ratio": 0.5, "rank": null, "rows": 5, "singular_threshold": 5, "skip": false, "training_ratio": 0.5, "window_size": 200}, "cp": [[0, 620], [621, 939], [940, 1265], [1266, 1532], [1533, 2024], [2025, 2370], [2371, 2886], [2887, 3241], [3242, 3691], [3692, 3996], [3997, 4234], [4235, 4491], [4492, 4977], [4978, 5224], [5225, 5475], [5476, 5725], [5726, 6045], [6046, 6931], [6932, 7252], [7253, 7653], [7654, 7872], [7873, 8429], [8430, 8824], [8825, 9327], [9328, 9810], [9811, 10168], [10169, 11564], [11565, 11846]], "score": {"metric": "compute_f1_score", "value": 0.1}}