{"status": "success", "error": "", "algorithm": "mssa_mw", "dataset": "hasc", "data_name": "HASC1017", "param": {"distance_threshold": 10, "normalize": true, "overlap_ratio": 0.5, "rank": null, "rows": 15, "singular_threshold": 5, "skip": false, "training_ratio": 0.6, "window_size": 700}, "cp": [[0, 1052], [1053, 2111], [2112, 3146], [3147, 4209], [4210, 5276], [5277, 6344], [6345, 7384], [7385, 8420], [8421, 9465], [9466, 10829], [10830, 11753], [11754, 11853]], "score": {"metric": "compute_f1_score", "value": 0.08333333333333333}}