{"status": "success", "error": "", "algorithm": "mssa_mw", "dataset": "hasc", "data_name": "HASC1009", "param": {"distance_threshold": 10, "normalize": true, "overlap_ratio": 0.0, "rank": null, "rows": 5, "singular_threshold": 5, "skip": false, "training_ratio": 0.5, "window_size": 200}, "cp": [[0, 445], [446, 860], [861, 1471], [1472, 1930], [1931, 2344], [2345, 2774], [2775, 3186], [3187, 3635], [3636, 4036], [4037, 4595], [4596, 4995], [4996, 5411], [5412, 5819], [5820, 6107], [6108, 6643], [6644, 7046], [7047, 7465], [7466, 7956], [7957, 8381], [8382, 8626], [8627, 9032], [9033, 9320], [9321, 9849], [9850, 10732], [10733, 11078], [11079, 11436], [11437, 11772]], "score": {"metric": "compute_f1_score", "value": 0.10256410256410256}}