{"status": "success", "error": "", "algorithm": "mssa_mw", "dataset": "hasc", "data_name": "HASC1008", "param": {"distance_threshold": 10, "normalize": true, "overlap_ratio": 0.0, "rank": null, "rows": 15, "singular_threshold": 2, "skip": false, "training_ratio": 0.5, "window_size": 400}, "cp": [[0, 409], [410, 1189], [1190, 1978], [1979, 2778], [2779, 3237], [3238, 4020], [4021, 4800], [4801, 5706], [5707, 6533], [6534, 7313], [7314, 8112], [8113, 8902], [8903, 9685], [9686, 10779], [10780, 11614], [11615, 11856]], "score": {"metric": "compute_f1_score", "value": 0.07142857142857144}}