{"status": "success", "error": "", "algorithm": "mssa_mw", "dataset": "hasc", "data_name": "HASC1005", "param": {"distance_threshold": 5, "normalize": true, "overlap_ratio": 0.9, "rank": null, "rows": 5, "singular_threshold": 2, "skip": false, "training_ratio": 0.6, "window_size": 400}, "cp": [[0, 629], [630, 1093], [1094, 1713], [1714, 2315], [2316, 2799], [2800, 3258], [3259, 3958], [3959, 4595], [4596, 5391], [5392, 5879], [5880, 6786], [6787, 7379], [7380, 8247], [8248, 8893], [8894, 9830], [9831, 10442], [10443, 10944], [10945, 11511], [11512, 11815]], "score": {"metric": "compute_f1_score", "value": 0.13333333333333333}}