{"status": "success", "error": "", "algorithm": "mssa_mw", "dataset": "hasc", "data_name": "HASC1014", "param": {"distance_threshold": 5, "normalize": true, "overlap_ratio": 0.5, "rank": null, "rows": 5, "singular_threshold": 5, "skip": false, "training_ratio": 0.5, "window_size": 700}, "cp": [[0, 1061], [1062, 2115], [2116, 3165], [3166, 4275], [4276, 5333], [5334, 6402], [6403, 7457], [7458, 9113], [9114, 10163], [10164, 11332], [11333, 11849]], "score": {"metric": "compute_f1_score", "value": 0.08695652173913043}}