{"status": "success", "error": "", "algorithm": "mssa_mw", "dataset": "hasc", "data_name": "HASC1014", "param": {"distance_threshold": 10, "normalize": true, "overlap_ratio": 0.0, "rank": null, "rows": 15, "singular_threshold": 2, "skip": false, "training_ratio": 0.5, "window_size": 400}, "cp": [[0, 898], [899, 1882], [1883, 2847], [2848, 3651], [3652, 4432], [4433, 5213], [5214, 6015], [6016, 7048], [7049, 7473], [7474, 8253], [8254, 9038], [9039, 9855], [9856, 10285], [10286, 11103], [11104, 11849]], "score": {"metric": "compute_f1_score", "value": 0.07407407407407407}}