{"status": "success", "error": "", "algorithm": "mssa_mw", "dataset": "hasc", "data_name": "HASC1011", "param": {"distance_threshold": 10, "normalize": true, "overlap_ratio": 0.0, "rank": null, "rows": 5, "singular_threshold": 2, "skip": false, "training_ratio": 0.5, "window_size": 700}, "cp": [[0, 704], [705, 1410], [1411, 2810], [2811, 3515], [3516, 4611], [4612, 6074], [6075, 7474], [7475, 8356], [8357, 9757], [9758, 10465], [10466, 11170], [11171, 11846]], "score": {"metric": "compute_f1_score", "value": 0.08333333333333333}}