{"status": "success", "error": "", "algorithm": "mssa_mw", "dataset": "hasc", "data_name": "HASC1009", "param": {"distance_threshold": 10, "normalize": true, "overlap_ratio": 0.9, "rank": null, "rows": 15, "singular_threshold": 5, "skip": false, "training_ratio": 0.6, "window_size": 400}, "cp": [[0, 683], [684, 2793], [2794, 3251], [3252, 4725], [4726, 5410], [5411, 5887], [5888, 6452], [6453, 6906], [6907, 8001], [8002, 9821], [9822, 10696], [10697, 11523], [11524, 11772]], "score": {"metric": "compute_f1_score", "value": 0.08}}