{"status": "success", "error": "", "algorithm": "mssa_mw", "dataset": "hasc", "data_name": "HASC1012", "param": {"distance_threshold": 10, "normalize": true, "overlap_ratio": 0.5, "rank": null, "rows": 15, "singular_threshold": 2, "skip": false, "training_ratio": 0.5, "window_size": 700}, "cp": [[0, 1037], [1038, 2074], [2075, 3109], [3110, 4145], [4146, 5210], [5211, 6247], [6248, 7282], [7283, 8326], [8327, 9366], [9367, 11123], [11124, 11742]], "score": {"metric": "compute_f1_score", "value": 0.08695652173913043}}