{"status": "success", "error": "", "algorithm": "mSSA", "dataset": "hasc", "data_name": "HASC1002", "param": {"distance_threshold": 5, "normalize": true, "rank": null, "rows": 15, "singular_threshold": 2, "skip": true, "training_ratio": 0.5, "window_size": 200}, "cp": [[0, 389], [390, 1094], [1095, 1649], [1650, 2039], [2040, 2669], [2670, 2879], [2880, 4139], [4140, 4589], [4590, 4844], [4845, 5414], [5415, 5804], [5805, 6254], [6255, 6959], [6960, 7349], [7350, 7769], [7770, 8954], [8955, 9599], [9600, 9959], [9960, 10619], [10620, 10919], [10920, 11767]], "score": {"metric": "compute_f1_score", "value": 0.12121212121212123}}