{"status": "success", "error": "", "algorithm": "mssa", "dataset": "hasc", "data_name": "HASC1015", "param": {"distance_threshold": 5, "normalize": true, "rank": null, "rows": 5, "singular_threshold": 2, "skip": true, "training_ratio": 0.6, "window_size": 50}, "cp": [[0, 1314], [1315, 1409], [1410, 2039], [2040, 2144], [2145, 2259], [2260, 2569], [2570, 2634], [2635, 2939], [2940, 2999], [3000, 3634], [3635, 3704], [3705, 3764], [3765, 3844], [3845, 4144], [4145, 4214], [4215, 4334], [4335, 4394], [4395, 5179], [5180, 5234], [5235, 5329], [5330, 5824], [5825, 5904], [5905, 6989], [6990, 10289], [10290, 10354], [10355, 10499], [10500, 10604], [10605, 11737]], "score": {"metric": "compute_f1_score", "value": 0.1}}