{"status": "success", "error": "", "algorithm": "mssa", "dataset": "hasc", "data_name": "HASC1006", "param": {"distance_threshold": 10, "normalize": false, "rank": null, "rows": 5, "singular_threshold": 5, "skip": false, "training_ratio": 0.6, "window_size": 400}, "cp": [[0, 865], [866, 1957], [1958, 2569], [2570, 3006], [3007, 3686], [3687, 4293], [4294, 4819], [4820, 5285], [5286, 6507], [6508, 6929], [6930, 7412], [7413, 7964], [7965, 8447], [8448, 9020], [9021, 9704], [9705, 10838], [10839, 11264], [11265, 11861]], "score": {"metric": "compute_f1_score", "value": 0.3225806451612903}}