{"status": "success", "error": "", "algorithm": "mSSA", "dataset": "hasc", "data_name": "HASC1001", "param": {"distance_threshold": 5, "normalize": false, "rank": null, "rows": 5, "singular_threshold": 2, "skip": false, "training_ratio": 0.6, "window_size": 400}, "cp": [[0, 719], [720, 1557], [1558, 2104], [2105, 2522], [2523, 2942], [2943, 3594], [3595, 4008], [4009, 4485], [4486, 4922], [4923, 6575], [6576, 7961], [7962, 8453], [8454, 8866], [8867, 9600], [9601, 10180], [10181, 10724], [10725, 11856]], "score": {"metric": "compute_f1_score", "value": 0.06896551724137931}}