{"status": "success", "error": "", "algorithm": "mssa", "dataset": "hasc", "data_name": "HASC1011", "param": {"distance_threshold": 5, "normalize": false, "rank": null, "rows": 15, "singular_threshold": 5, "skip": false, "training_ratio": 0.6, "window_size": 400}, "cp": [[0, 403], [404, 799], [800, 1283], [1284, 2045], [2046, 2678], [2679, 3377], [3378, 3922], [3923, 4375], [4376, 5012], [5013, 5991], [5992, 6750], [6751, 7181], [7182, 7770], [7771, 8227], [8228, 9017], [9018, 9526], [9527, 10114], [10115, 10553], [10554, 11052], [11053, 11735], [11736, 11846]], "score": {"metric": "compute_f1_score", "value": 0.060606060606060615}}