{"status": "success", "error": "", "algorithm": "mssa", "dataset": "hasc", "data_name": "HASC1002", "param": {"distance_threshold": 10, "normalize": false, "rank": null, "rows": 5, "singular_threshold": 2, "skip": false, "training_ratio": 0.6, "window_size": 700}, "cp": [[0, 1082], [1083, 2054], [2055, 2855], [2856, 3697], [3698, 4846], [4847, 5693], [5694, 7084], [7085, 7813], [7814, 9093], [9094, 9850], [9851, 10690], [10691, 11510], [11511, 11767]], "score": {"metric": "compute_f1_score", "value": 0.4}}