{"status": "success", "error": "", "algorithm": "mSSA", "dataset": "hasc", "data_name": "HASC1005", "param": {"distance_threshold": 5, "normalize": true, "rank": null, "rows": 30, "singular_threshold": 5, "skip": false, "training_ratio": 0.6, "window_size": 700}, "cp": [[0, 1667], [1668, 2554], [2555, 3403], [3404, 4098], [4099, 5155], [5156, 5886], [5887, 7104], [7105, 7960], [7961, 8942], [8943, 9700], [9701, 10943], [10944, 11815]], "score": {"metric": "compute_f1_score", "value": 0.08695652173913043}}