{"status": "success", "error": "", "algorithm": "mssa", "dataset": "hasc", "data_name": "HASC1011", "param": {"distance_threshold": 5, "normalize": true, "rank": null, "rows": 5, "singular_threshold": 5, "skip": false, "training_ratio": 0.6, "window_size": 700}, "cp": [[0, 730], [731, 2252], [2253, 3042], [3043, 3928], [3929, 4733], [4734, 5478], [5479, 6471], [6472, 7176], [7177, 9185], [9186, 10021], [10022, 10857], [10858, 11846]], "score": {"metric": "compute_f1_score", "value": 0.08333333333333333}}