{"status": "success", "error": "", "algorithm": "mssa", "dataset": "hasc", "data_name": "HASC1002", "param": {"distance_threshold": 10, "normalize": true, "rank": null, "rows": 5, "singular_threshold": 5, "skip": false, "training_ratio": 0.6, "window_size": 700}, "cp": [[0, 1082], [1083, 2084], [2085, 2855], [2856, 4089], [4090, 4842], [4843, 5701], [5702, 7028], [7029, 7839], [7840, 9103], [9104, 9891], [9892, 10688], [10689, 11767]], "score": {"metric": "compute_f1_score", "value": 0.4166666666666667}}