{"status": "success", "error": "", "algorithm": "mSSA", "dataset": "hasc", "data_name": "HASC1003", "param": {"distance_threshold": 10, "normalize": true, "rank": null, "rows": 15, "singular_threshold": 5, "skip": true, "training_ratio": 0.5, "window_size": 200}, "cp": [[0, 629], [630, 944], [945, 1754], [1755, 2789], [2790, 3284], [3285, 4184], [4185, 4664], [4665, 5009], [5010, 5594], [5595, 5894], [5895, 7274], [7275, 7634], [7635, 8699], [8700, 9029], [9030, 9404], [9405, 9974], [9975, 10289], [10290, 11249], [11250, 11999]], "score": {"metric": "compute_f1_score", "value": 0.06666666666666667}}