{"status": "success", "error": "", "algorithm": "mssa", "dataset": "hasc", "data_name": "HASC1001", "param": {"distance_threshold": 10, "normalize": false, "rank": null, "rows": 5, "singular_threshold": 2, "skip": false, "training_ratio": 0.6, "window_size": 400}, "cp": [[0, 721], [722, 1712], [1713, 2292], [2293, 2772], [2773, 4220], [4221, 4811], [4812, 5547], [5548, 6104], [6105, 6879], [6880, 7285], [7286, 7703], [7704, 8154], [8155, 8597], [8598, 9855], [9856, 10450], [10451, 11066], [11067, 11774], [11775, 11856]], "score": {"metric": "compute_f1_score", "value": 0.06666666666666667}}