{"status": "success", "error": "", "algorithm": "mSSA", "dataset": "hasc", "data_name": "HASC1002", "param": {"distance_threshold": 10, "normalize": false, "rank": null, "rows": 30, "singular_threshold": 2, "skip": false, "training_ratio": 0.5, "window_size": 700}, "cp": [[0, 1079], [1080, 1846], [1847, 2864], [2865, 4120], [4121, 4839], [4840, 5766], [5767, 6990], [6991, 7850], [7851, 8555], [8556, 9954], [9955, 10685], [10686, 11492], [11493, 11767]], "score": {"metric": "compute_f1_score", "value": 0.4}}