{"status": "success", "error": "", "algorithm": "mssa", "dataset": "hasc", "data_name": "HASC1006", "param": {"distance_threshold": 10, "normalize": false, "rank": null, "rows": 15, "singular_threshold": 5, "skip": false, "training_ratio": 0.6, "window_size": 700}, "cp": [[0, 698], [699, 1862], [1863, 2865], [2866, 3642], [3643, 4884], [4885, 5698], [5699, 6921], [6922, 7633], [7634, 8515], [8516, 9973], [9974, 10785], [10786, 11861]], "score": {"metric": "compute_f1_score", "value": 0.24000000000000002}}