{"status": "success", "error": "", "algorithm": "mssa", "dataset": "hasc", "data_name": "HASC1004", "param": {"distance_threshold": 5, "normalize": false, "rank": null, "rows": 5, "singular_threshold": 5, "skip": true, "training_ratio": 0.5, "window_size": 50}, "cp": [[0, 804], [805, 1679], [1680, 1754], [1755, 4159], [4160, 8109], [8110, 8539], [8540, 8639], [8640, 8839], [8840, 9269], [9270, 9339], [9340, 9414], [9415, 10039], [10040, 10204], [10205, 10749], [10750, 10909], [10910, 11014], [11015, 11134], [11135, 11249], [11250, 11349], [11350, 11842]], "score": {"metric": "compute_f1_score", "value": 0.12903225806451613}}