{"status": "success", "error": "", "algorithm": "mssa", "dataset": "hasc", "data_name": "HASC1014", "param": {"distance_threshold": 10, "normalize": false, "rank": null, "rows": 5, "singular_threshold": 2, "skip": false, "training_ratio": 0.6, "window_size": 700}, "cp": [[0, 701], [702, 2373], [2374, 3291], [3292, 4080], [4081, 5393], [5394, 6291], [6292, 7005], [7006, 8041], [8042, 9111], [9112, 9836], [9837, 10813], [10814, 11849]], "score": {"metric": "compute_f1_score", "value": 0.08333333333333333}}