{"status": "success", "error": "", "algorithm": "mssa_mw", "dataset": "hasc", "data_name": "HASC1016", "param": {"distance_threshold": 5, "normalize": true, "overlap_ratio": 0.0, "rank": null, "rows": 15, "singular_threshold": 2, "skip": false, "training_ratio": 0.6, "window_size": 700}, "cp": [[0, 1379], [1380, 2759], [2760, 3488], [3489, 4869], [4870, 6260], [6261, 7640], [7641, 9057], [9058, 10437], [10438, 11821], [11822, 11999]], "score": {"metric": "compute_f1_score", "value": 0.0909090909090909}}