{"status": "success", "error": "", "algorithm": "mssa_mw", "dataset": "hasc", "data_name": "HASC1010", "param": {"distance_threshold": 5, "normalize": true, "overlap_ratio": 0.9, "rank": null, "rows": 5, "singular_threshold": 5, "skip": false, "training_ratio": 0.5, "window_size": 200}, "cp": [[0, 425], [426, 659], [660, 889], [890, 1099], [1100, 1311], [1312, 1516], [1517, 2987], [2988, 3283], [3284, 3559], [3560, 3821], [3822, 4989], [4990, 5591], [5592, 5867], [5868, 6161], [6162, 6929], [6930, 7239], [7240, 7444], [7445, 7830], [7831, 8072], [8073, 8341], [8342, 8919], [8920, 9396], [9397, 10973], [10974, 11267], [11268, 11521], [11522, 11782], [11783, 11990], [11991, 11999]], "score": {"metric": "compute_f1_score", "value": 0.05}}