{"status": "success", "error": "", "algorithm": "mssa_mw", "dataset": "hasc", "data_name": "HASC1015", "param": {"distance_threshold": 10, "normalize": true, "overlap_ratio": 0.0, "rank": null, "rows": 5, "singular_threshold": 2, "skip": false, "training_ratio": 0.5, "window_size": 200}, "cp": [[0, 553], [554, 997], [998, 1408], [1409, 1814], [1815, 2216], [2217, 2676], [2677, 3076], [3077, 3655], [3656, 4103], [4104, 4516], [4517, 4925], [4926, 5331], [5332, 5791], [5792, 6196], [6197, 6597], [6598, 7024], [7025, 7342], [7343, 7612], [7613, 8013], [8014, 8464], [8465, 8894], [8895, 9165], [9166, 9572], [9573, 9972], [9973, 10179], [10180, 10635], [10636, 11176], [11177, 11606], [11607, 11737]], "score": {"metric": "compute_f1_score", "value": 0.0975609756097561}}