{"status": "success", "error": "", "algorithm": "mssa_mw", "dataset": "hasc", "data_name": "HASC1015", "param": {"distance_threshold": 10, "normalize": true, "overlap_ratio": 0.0, "rank": null, "rows": 5, "singular_threshold": 2, "skip": false, "training_ratio": 0.6, "window_size": 400}, "cp": [[0, 810], [811, 1611], [1612, 2411], [2412, 3211], [3212, 4013], [4014, 4814], [4815, 5615], [5616, 6415], [6416, 7215], [7216, 8017], [8018, 8898], [8899, 9707], [9708, 10617], [10618, 11420], [11421, 11737]], "score": {"metric": "compute_f1_score", "value": 0.07407407407407407}}