{"status": "success", "error": "", "algorithm": "hybrid_cusum", "dataset": "mean", "data_name": "mean14", "param": {"distance_threshold": 10, "rank": null, "rows": 15, "singular_threshold": 5, "skip": false, "training_ratio": 0.6, "window_size": 200}, "cp": [[0, 492], [493, 705], [706, 907], [908, 1216], [1217, 1416], [1417, 2003], [2004, 2202], [2203, 2436], [2437, 2669], [2670, 2901], [2902, 3149], [3150, 3384], [3385, 3614], [3615, 4000], [4001, 4240], [4241, 4999]], "score": {"metric": "compute_f1_score", "value": 0.2727272727272727}}