{"status": "success", "error": "", "algorithm": "microsoft_ssa", "dataset": "mean", "data_name": "mean9", "param": {"change_history_length": 10, "confidence": 95.0, "error_function": "SignedDifference", "martingale": "Mixture", "power_martingale_epsilon": 0.1, "seasonal_window_size": 5, "training_window_size": 700}, "cp": [[0, 8], [9, 33], [34, 378], [379, 515], [516, 619], [620, 860], [861, 1102], [1103, 1342], [1343, 1585], [1586, 1826], [1827, 1930], [1931, 2171], [2172, 2413], [2414, 2654], [2655, 2758], [2759, 2895], [2896, 2999], [3000, 3208], [3209, 3241], [3242, 3482], [3483, 3691], [3692, 4311], [4312, 4518], [4519, 4760], [4761, 4999]], "score": {"metric": "compute_f1_score", "value": 0.12903225806451613}}