{"status": "success", "error": "", "algorithm": "microsoft_ssa", "dataset": "mean", "data_name": "mean1", "param": {"change_history_length": 10, "confidence": 95.0, "error_function": "AbsoluteDifference", "martingale": "Power", "power_martingale_epsilon": 0.1, "seasonal_window_size": 30, "training_window_size": 200}, "cp": [[0, 145], [146, 1005], [1006, 1575], [1576, 2006], [2007, 2999], [3000, 3613], [3614, 3721], [3722, 3949], [3950, 4005], [4006, 4334], [4335, 4999]], "score": {"metric": "compute_f1_score", "value": 0.5882352941176471}}