{"status": "success", "error": "", "algorithm": "microsoft_ssa", "dataset": "mean", "data_name": "mean2", "param": {"change_history_length": 10, "confidence": 95.0, "error_function": "SignedProportion", "martingale": "Mixture", "power_martingale_epsilon": 0.5, "seasonal_window_size": 5, "training_window_size": 400}, "cp": [[0, 36], [37, 56], [57, 84], [85, 94], [95, 139], [140, 198], [199, 208], [209, 249], [250, 259], [260, 296], [297, 307], [308, 323], [324, 353], [354, 363], [364, 377], [378, 418], [419, 463], [464, 473], [474, 521], [522, 531], [532, 541], [542, 588], [589, 631], [632, 641], [642, 653], [654, 678], [679, 734], [735, 753], [754, 792], [793, 802], [803, 812], [813, 845], [846, 855], [856, 865], [866, 902], [903, 921], [922, 948], [949, 958], [959, 968], [969, 978], [979, 1006], [1007, 1059], [1060, 1069], [1070, 4999]], "score": {"metric": "compute_f1_score", "value": 0.08}}