{"status": "success", "error": "", "algorithm": "microsoft_ssa", "dataset": "struct", "data_name": "struct1", "param": {"change_history_length": 10, "confidence": 95.0, "error_function": "SignedDifference", "martingale": "Mixture", "power_martingale_epsilon": 0.5, "seasonal_window_size": 30, "training_window_size": 400}, "cp": [[0, 9], [10, 919], [920, 999], [1000, 2179], [2180, 2265], [2266, 2308], [2309, 2390], [2391, 2451], [2452, 2622], [2623, 2634], [2635, 2970], [2971, 2985], [2986, 2999], [3000, 4239], [4240, 4511], [4512, 4753], [4754, 4999]], "score": {"metric": "compute_f1_score", "value": 0.2608695652173913}}