{"status": "success", "error": "", "algorithm": "microsoft_ssa", "dataset": "struct", "data_name": "struct12", "param": {"change_history_length": 10, "confidence": 95.0, "error_function": "SignedDifference", "martingale": "Mixture", "power_martingale_epsilon": 0.1, "seasonal_window_size": 15, "training_window_size": 400}, "cp": [[0, 828], [829, 999], [1000, 1009], [1010, 1131], [1132, 1181], [1182, 1231], [1232, 1354], [1355, 1404], [1405, 1580], [1581, 1628], [1629, 1860], [1861, 1985], [1986, 2067], [2068, 2131], [2132, 2173], [2174, 2215], [2216, 2301], [2302, 2315], [2316, 2459], [2460, 2750], [2751, 2765], [2766, 2993], [2994, 3003], [3004, 4428], [4429, 4999]], "score": {"metric": "compute_f1_score", "value": 0.1935483870967742}}