{"status": "success", "error": "", "algorithm": "microsoft_ssa", "dataset": "struct", "data_name": "struct1", "param": {"change_history_length": 10, "confidence": 95.0, "error_function": "SquaredDifference", "martingale": "Mixture", "power_martingale_epsilon": 0.5, "seasonal_window_size": 30, "training_window_size": 400}, "cp": [[0, 8], [9, 126], [127, 224], [225, 319], [320, 354], [355, 407], [408, 490], [491, 532], [533, 765], [766, 786], [787, 810], [811, 864], [865, 878], [879, 998], [999, 1008], [1009, 2999], [3000, 3012], [3013, 3022], [3023, 4018], [4019, 4999]], "score": {"metric": "compute_f1_score", "value": 0.23076923076923075}}