{"status": "success", "error": "", "algorithm": "microsoft_ssa", "dataset": "struct", "data_name": "struct7", "param": {"change_history_length": 10, "confidence": 95.0, "error_function": "AbsoluteDifference", "martingale": "Mixture", "power_martingale_epsilon": 0.1, "seasonal_window_size": 15, "training_window_size": 200}, "cp": [[0, 158], [159, 610], [611, 675], [676, 830], [831, 999], [1000, 1160], [1161, 1402], [1403, 1770], [1771, 1839], [1840, 1999], [2000, 2294], [2295, 2605], [2606, 2643], [2644, 2694], [2695, 2999], [3000, 4720], [4721, 4999]], "score": {"metric": "compute_f1_score", "value": 0.3478260869565218}}