{"status": "success", "error": "", "algorithm": "hybrid_cusum", "dataset": "struct", "data_name": "struct6", "param": {"distance_threshold": 10, "rank": null, "rows": 15, "singular_threshold": 2, "skip": false, "training_ratio": 0.6, "window_size": 200}, "cp": [[0, 237], [238, 570], [571, 936], [937, 1219], [1220, 1509], [1510, 1788], [1789, 2000], [2001, 2313], [2314, 2540], [2541, 2788], [2789, 3000], [3001, 3417], [3418, 3618], [3619, 3818], [3819, 4033], [4034, 4396], [4397, 4599], [4600, 4799], [4800, 4999]], "score": {"metric": "compute_f1_score", "value": 0.23999999999999996}}