{"status": "success", "error": "", "algorithm": "hybrid_cusum", "dataset": "struct", "data_name": "struct18", "param": {"distance_threshold": 10, "rank": null, "rows": 15, "singular_threshold": 2, "skip": false, "training_ratio": 0.5, "window_size": 200}, "cp": [[0, 215], [216, 433], [434, 646], [647, 891], [892, 1197], [1198, 1530], [1531, 1914], [1915, 2190], [2191, 2469], [2470, 2941], [2942, 3150], [3151, 4007], [4008, 4999]], "score": {"metric": "compute_f1_score", "value": 0.21052631578947367}}