{"status": "success", "error": "", "algorithm": "mssa_mw_dist", "dataset": "hasc", "data_name": "HASC1010", "param": {"distance_threshold": 10, "normalize": true, "rank": null, "rows": 5, "skip": false, "training_ratio": 0.5, "window_size": 700}, "cp": [[0, 3194], [3195, 3934], [3935, 4639], [4640, 5347], [5348, 6055], [6056, 15199], [15200, 16774], [16775, 17604], [17605, 18478], [18479, 21769], [21770, 22476], [22477, 23290], [23291, 24216], [24217, 24921], [24922, 33008], [33009, 33796], [33797, 35724], [35725, 35999]], "score": {"metric": "compute_f1_score", "value": 0.06666666666666667}}